{
  "data": {
    "type": "provider-docs",
    "id": "3254712",
    "attributes": {
      "category": "data-sources",
      "content": "---\nsubcategory: \"VPC Lattice\"\nlayout: \"aws\"\npage_title: \"AWS: aws_vpclattice_listener\"\ndescription: |-\n  Terraform data source for managing an AWS VPC Lattice Listener.\n---\n\n# Data Source: aws_vpclattice_listener\n\nTerraform data source for managing an AWS VPC Lattice Listener.\n\n## Example Usage\n\n### Basic Usage\n\n```terraform\ndata \"aws_vpclattice_listener\" \"example\" {\n}\n```\n\n## Argument Reference\n\nThe following arguments are required:\n\n* `service_identifier` - (Required) ID or Amazon Resource Name (ARN) of the service network\n* `listener_identifier` - (Required) ID or Amazon Resource Name (ARN) of the listener\n\n## Attribute Reference\n\nThis data source exports the following attributes in addition to the arguments above:\n\n* `arn` - ARN of the listener.\n* `created_at` - The date and time that the listener was created.\n* `default_action` - The actions for the default listener rule.\n* `last_updated_at` - The date and time the listener was last updated.\n* `listener_id` - The ID of the listener.\n* `name` - The name of the listener.\n* `port` - The listener port.\n* `protocol` - The listener protocol. Either `HTTPS` or `HTTP`.\n* `service_arn` - The ARN of the service.\n* `service_id` - The ID of the service.\n* `tags` - List of tags associated with the listener.\n",
      "language": "hcl",
      "path": "website/docs/d/vpclattice_listener.html.markdown",
      "slug": "vpclattice_listener",
      "subcategory": "VPC Lattice",
      "title": "vpclattice_listener",
      "truncated": false
    },
    "links": {
      "self": "/v2/provider-docs/3254712"
    }
  }
}